[
  {
    "month": "January",
    "name": "Atik & Parveen",
    "date": "8th January",
    "event": "Wedding",
    "format": "2026-01-08"
  },
  {
    "month": "January",
    "name": "Rehana",
    "date": "8th January",
    "event": "Birthday",
    "format": "2026-01-08"
  },
  {
    "month": "January",
    "name": "Atik",
    "date": "21st January",
    "event": "Birthday",
    "format": "2026-01-21"
  },
  {
    "month": "February",
    "name": "Nana(Rahmatullah)",
    "date": "10th February",
    "event": "Birthday",
    "format": "2026-02-10"
  },
  {
    "month": "February",
    "name": "Fardeen",
    "date": "16th February",
    "event": "Birthday",
    "format": "2026-02-16"
  },
  {
    "month": "March",
    "name": "Raees & Choti",
    "date": "5th March",
    "event": "Wedding",
    "format": "2026-03-05"
  },
  {
    "month": "March",
    "name": "Shabina",
    "date": "5th March",
    "event": "Birthday",
    "format": "2026-03-05"
  },
  {
    "month": "March",
    "name": "Parveen",
    "date": "30th March",
    "event": "Birthday",
    "format": "2026-03-30"
  },
  {
    "month": "April",
    "name": "Ayesha",
    "date": "8th April",
    "event": "Birthday",
    "format": "2026-04-08"
  },
  {
    "month": "April",
    "name": "Ashraf & Sheza",
    "date": "11th April",
    "event": "Birthday",
    "format": "2026-04-11"
  },
  {
    "month": "April",
    "name": "Ameera",
    "date": "15th April",
    "event": "Birthday",
    "format": "2026-04-15"
  },
  {
    "month": "April",
    "name": "Nasreen",
    "date": "29th April",
    "event": "Birthday",
    "format": "2026-04-29"
  },
  {
    "month": "April",
    "name": "Rafik",
    "date": "30th April",
    "event": "Birthday",
    "format": "2026-04-30"
  },
  {
    "month": "May",
    "name": "Adnan",
    "date": "14th May",
    "event": "Birthday",
    "format": "2026-05-14"
  },
  {
    "month": "May",
    "name": "Shafik & Nasreen",
    "date": "19th May",
    "event": "Wedding",
    "format": "2026-05-19"
  },
  {
    "month": "May",
    "name": "Shafik",
    "date": "26th May",
    "event": "Birthday",
    "format": "2026-05-26"
  },
  {
    "month": "June",
    "name": "Momina",
    "date": "12th June",
    "event": "Birthday",
    "format": "2026-06-12"
  },
  {
    "month": "July",
    "name": "Saira",
    "date": "4th July",
    "event": "Birthday",
    "format": "2026-07-04"
  },
  {
    "month": "July",
    "name": "Choti",
    "date": "9th July",
    "event": "Birthday",
    "format": "2026-07-09"
  },
  {
    "month": "July",
    "name": "Shakil",
    "date": "24th July",
    "event": "Birthday",
    "format": "2026-07-24"
  },
  {
    "month": "August",
    "name": "Aqsa",
    "date": "4th August",
    "event": "Birthday",
    "format": "2026-08-04"
  },
  {
    "month": "August",
    "name": "Rafik & Amina",
    "date": "7th August",
    "event": "Wedding",
    "format": "2026-08-07"
  },
  {
    "month": "August",
    "name": "Rukshana & Zakir",
    "date": "8th August",
    "event": "Wedding",
    "format": "2026-08-08"
  },
  {
    "month": "August",
    "name": "Inaya & Iqra",
    "date": "22nd August",
    "event": "Birthday",
    "format": "2026-08-22"
  },
  {
    "month": "August",
    "name": "Saima",
    "date": "24th August",
    "event": "Birthday",
    "format": "2026-08-24"
  },
  {
    "month": "September",
    "name": "Rukshana",
    "date": "21st September",
    "event": "Birthday",
    "format": "2026-09-21"
  },
  {
    "month": "September",
    "name": "Amina",
    "date": "23rd September",
    "event": "Birthday",
    "format": "2026-09-23"
  },
  {
    "month": "September",
    "name": "Namra",
    "date": "25th September",
    "event": "Birthday",
    "format": "2026-09-25"
  },
  {
    "month": "October",
    "name": "Shehzad",
    "date": "3rd October",
    "event": "Birthday",
    "format": "2026-10-03"
  },
  {
    "month": "October",
    "name": "Rizwan",
    "date": "15th October",
    "event": "Birthday",
    "format": "2026-10-15"
  },
  {
    "month": "November",
    "name": "Nabila",
    "date": "17th November",
    "event": "Birthday",
    "format": "2026-11-17"
  },
  {
    "month": "November",
    "name": "Shakil & Momina",
    "date": "21st November",
    "event": "Wedding",
    "format": "2026-11-21"
  },
  {
    "month": "December",
    "name": "Raees",
    "date": "1st December",
    "event": "Birthday",
    "format": "2026-12-01"
  },
  {
    "month": "December",
    "name": "Nani(Noorjahan)",
    "date": "23rd December",
    "event": "Demise",
    "format": "2026-12-23"
  },
  {
    "month": "December",
    "name": "Nani(Noorjahan)",
    "date": "30th December",
    "event": "Birthday",
    "format": "2026-12-30"
  }
]
